libname/__init__.py
libname/quicklook_time_series.py
quicklooktimeseries-0.0.1.dist-info/METADATA
quicklooktimeseries-0.0.1.dist-info/WHEEL
quicklooktimeseries-0.0.1.dist-info/top_level.txt
quicklooktimeseries-0.0.1.dist-info/RECORD
