Metadata-Version: 2.1
Name: quicklooktimeseries
Version: 0.0.1
Summary: quicklook time series data
Home-page: UNKNOWN
Author: Hong Tang
Author-email: <stanghong@gmail.com>
License: UNKNOWN
Keywords: python,timeseries,plot
Platform: UNKNOWN
Classifier: Development Status :: 1 - Planning
Classifier: Intended Audience :: Developers
Classifier: Programming Language :: Python :: 3
Classifier: Operating System :: Unix
Classifier: Operating System :: MacOS :: MacOS X
Classifier: Operating System :: Microsoft :: Windows
Requires-Dist: python
Requires-Dist: pandas
